floyd_warshall_alg/__init__.py
floyd_warshall_alg/common_func/__init__.py
floyd_warshall_alg/common_func/generate_data.py
floyd_warshall_alg/common_func/load_testing_measurements.py
floyd_warshall_alg/common_func/main.py
floyd_warshall_alg/simple_algorithm.py
floyd_warshall_alg-0.1.2.dist-info/entry_points.txt
floyd_warshall_alg-0.1.2.dist-info/WHEEL
floyd_warshall_alg-0.1.2.dist-info/METADATA
floyd_warshall_alg-0.1.2.dist-info/RECORD
