Metadata-Version: 2.1
Name: floyd-warshall-alg
Version: 0.1.2
Summary: 
Author: Your Name
Author-email: you@example.com
Requires-Python: >=3.8,<4.0
Classifier: Programming Language :: Python :: 3
Classifier: Programming Language :: Python :: 3.8
Classifier: Programming Language :: Python :: 3.9
Requires-Dist: Cycler (==0.10.0)
Requires-Dist: Pillow (==8.2.0)
Requires-Dist: click (>=8.0.1,<9.0.0)
Requires-Dist: kiwisolver (==1.3.1)
Requires-Dist: matplotlib (==3.4.2)
Requires-Dist: numpy (==1.20.3)
Requires-Dist: pandas (==1.2.4)
Requires-Dist: pyparsing (==2.4.7)
Requires-Dist: python-dateutil (==2.8.1)
Requires-Dist: pytz (==2021.1)
Requires-Dist: six (==1.16.0)
